activefence_client_sdk/__init__.py
activefence_client_sdk/client.py
activefence_client_sdk/models.py
activefence_client_sdk/utils.py
activefence_client_sdk-0.0.11.dist-info/licenses/LICENSE
activefence_client_sdk-0.0.11.dist-info/METADATA
activefence_client_sdk-0.0.11.dist-info/WHEEL
activefence_client_sdk-0.0.11.dist-info/top_level.txt
activefence_client_sdk-0.0.11.dist-info/RECORD
