Metadata-Version: 2.4
Name: activefence_client_sdk
Version: 0.0.11
Summary: ActiveFence Client SDK
Project-URL: repository, https://github.com/ActiveFence/activefence_client_sdk
Classifier: Programming Language :: Python :: 3
Classifier: Operating System :: OS Independent
Requires-Python: >=3.9
License-File: LICENSE
Requires-Dist: aiohttp~=3.12
Requires-Dist: requests~=2.32
Requires-Dist: pydantic<3.0,>=2.0
Provides-Extra: dev
Requires-Dist: pytest; extra == "dev"
Requires-Dist: pytest-asyncio; extra == "dev"
Requires-Dist: aioresponses; extra == "dev"
Requires-Dist: responses; extra == "dev"
Requires-Dist: ruff; extra == "dev"
Requires-Dist: pre-commit; extra == "dev"
Requires-Dist: mypy; extra == "dev"
Requires-Dist: types-requests; extra == "dev"
Dynamic: license-file
